aioresponses/__init__.py
aioresponses/compat.py
aioresponses/core.py
aioresponses/py.typed
aioresponses-0.7.6.dist-info/AUTHORS
aioresponses-0.7.6.dist-info/AUTHORS.rst
aioresponses-0.7.6.dist-info/LICENSE
aioresponses-0.7.6.dist-info/METADATA
aioresponses-0.7.6.dist-info/WHEEL
aioresponses-0.7.6.dist-info/pbr.json
aioresponses-0.7.6.dist-info/top_level.txt
aioresponses-0.7.6.dist-info/RECORD
